verilog/rtl/half_adder.v
module half_adder(
    input a,b,
    output sum,carry
);
assign sum =a^b;
assign carry=a&b;

endmodule

verilog/rtl/multiplier_2x2.v
module  multiplier_2x2 (
    input [1:0]a,b,
    output [3:0]p);
wire ppo,pp1,pp2,pp3;
wire c1;
assign ppo=a[0]&b[0];
assign pp1=a[1]&b[0];
assign pp2=a[0]&b[1];
assign pp3=a[1]&b[1];
assign p[0]=ppo;
half_adder uu1(.a(pp1),.b(pp2),.sum(p[1]),.carry(c1));
half_adder uu2(.a(pp3),.b(c1),.sum(p[2]),.carry(p[3]));

endmodule

verilog/tb/tb_multiplier_2x2.v
`timescale 1ns/1ps

module tb_multiplier_2x2;

reg [1:0] a;
reg [1:0] b;
wire [3:0] p;

multiplier_2x2 uut (
    .a(a),
    .b(b),
    .p(p)
);

initial begin
    
    $dumpfile("sim/wave.vcd");
    $dumpvars(0, tb_multiplier_2x2);

    $display("-------------------------------");
    $display(" Time\tA\tB\tProduct");
    $display("-------------------------------");

    a=2'b00; b=2'b00; #10;
    a=2'b00; b=2'b01; #10;
    a=2'b00; b=2'b10; #10;
    a=2'b00; b=2'b11; #10;

    a=2'b01; b=2'b00; #10;
    a=2'b01; b=2'b01; #10;
    a=2'b01; b=2'b10; #10;
    a=2'b01; b=2'b11; #10;

    a=2'b10; b=2'b00; #10;
    a=2'b10; b=2'b01; #10;
    a=2'b10; b=2'b10; #10;
    a=2'b10; b=2'b11; #10;

    a=2'b11; b=2'b00; #10;
    a=2'b11; b=2'b01; #10;
    a=2'b11; b=2'b10; #10;
    a=2'b11; b=2'b11; #10;

    $finish;
end

initial begin
    $monitor("%4t\t%b\t%b\t%b", $time, a, b, p);
end

endmodule

verilog/sim/wave.vcd
$date
	Sun Jul 19 19:00:14 2026
$end
$version
	Icarus Verilog
$end
$timescale
	1ps
$end
$scope module tb_multiplier_2x2 $end
$var wire 4 ! p [3:0] $end
$var reg 2 " a [1:0] $end
$var reg 2 # b [1:0] $end
$scope module uut $end
$var wire 2 $ a [1:0] $end
$var wire 2 % b [1:0] $end
$var wire 1 & pp1 $end
$var wire 1 ' pp2 $end
$var wire 1 ( pp3 $end
$var wire 1 ) ppo $end
$var wire 4 * p [3:0] $end
$var wire 1 + c1 $end
$scope module uu1 $end
$var wire 1 & a $end
$var wire 1 ' b $end
$var wire 1 + carry $end
$var wire 1 , sum $end
$upscope $end
$scope module uu2 $end
$var wire 1 ( a $end
$var wire 1 + b $end
$var wire 1 - carry $end
$var wire 1 . sum $end
$upscope $end
$upscope $end
$upscope $end
$enddefinitions $end
$comment Show the parameter values. $end
$dumpall
$end
#0
$dumpvars
0.
0-
0,
0+
b0 *
0)
0(
0'
0&
b0 %
b0 $
b0 #
b0 "
b0 !
$end
#10000
b1 #
b1 %
#20000
b10 #
b10 %
#30000
b11 #
b11 %
#40000
b0 #
b0 %
b1 "
b1 $
#50000
b1 !
b1 *
1)
b1 #
b1 %
#60000
1,
b10 !
b10 *
0)
1'
b10 #
b10 %
#70000
b11 !
b11 *
1)
b11 #
b11 %
#80000
0,
b0 !
b0 *
0)
0'
b0 #
b0 %
b10 "
b10 $
#90000
b10 !
b10 *
1,
1&
b1 #
b1 %
#100000
0,
b100 !
b100 *
1.
0&
1(
b10 #
b10 %
#110000
b110 !
b110 *
1,
1&
b11 #
b11 %
#120000
0,
b0 !
b0 *
0.
0&
0(
b0 #
b0 %
b11 "
b11 $
#130000
1,
b11 !
b11 *
1)
1&
b1 #
b1 %
#140000
1.
b110 !
b110 *
0)
0&
1'
1(
b10 #
b10 %
#150000
0.
1-
0,
1+
b1001 !
b1001 *
1)
1&
b11 #
b11 %
